langchain_astarcloud/__init__.py
langchain_astarcloud/chat_astarcloud.py
langchain_astarcloud-0.1.22.dist-info/licenses/LICENSE
langchain_astarcloud-0.1.22.dist-info/METADATA
langchain_astarcloud-0.1.22.dist-info/WHEEL
langchain_astarcloud-0.1.22.dist-info/top_level.txt
langchain_astarcloud-0.1.22.dist-info/RECORD
