Metadata-Version: 2.4
Name: langchain-astarcloud
Version: 0.1.22
Summary: LangChain integration for AstarCloud chat models
Author-email: AstarCloud <support@astarcloud.no>
License: MIT
Project-URL: Homepage, https://github.com/ASTAR-CLOUD/langchain_astarcloud
Project-URL: Repository, https://github.com/ASTAR-CLOUD/langchain_astarcloud
Project-URL: Bug Tracker, https://github.com/ASTAR-CLOUD/langchain_astarcloud/issues
Project-URL: Documentation, https://github.com/ASTAR-CLOUD/langchain_astarcloud#readme
Keywords: langchain,astarcloud,llm,chat,ai
Classifier: Development Status :: 4 - Beta
Classifier: Intended Audience :: Developers
Classifier: Topic :: Scientific/Engineering :: Artificial Intelligence
Classifier: Topic :: Software Development :: Libraries :: Python Modules
Classifier: Programming Language :: Python :: 3
Classifier: Programming Language :: Python :: 3.8
Classifier: Programming Language :: Python :: 3.9
Classifier: Programming Language :: Python :: 3.10
Classifier: Programming Language :: Python :: 3.11
Classifier: Programming Language :: Python :: 3.12
Classifier: License :: OSI Approved :: MIT License
Classifier: Operating System :: OS Independent
Requires-Python: >=3.8
License-File: LICENSE
Requires-Dist: langchain-core>=0.1.0
Requires-Dist: astarcloud>=0.1.14
Provides-Extra: dev
Requires-Dist: pytest>=7.0; extra == "dev"
Requires-Dist: pytest-asyncio; extra == "dev"
Requires-Dist: black; extra == "dev"
Requires-Dist: isort; extra == "dev"
Requires-Dist: mypy; extra == "dev"
Requires-Dist: ruff; extra == "dev"
Dynamic: license-file
